alphashapy/__init__.py
alphashapy/negative_alphahull.py
alphashapy-0.2.0.dist-info/LICENSE
alphashapy-0.2.0.dist-info/METADATA
alphashapy-0.2.0.dist-info/WHEEL
alphashapy-0.2.0.dist-info/top_level.txt
alphashapy-0.2.0.dist-info/RECORD
