Metadata-Version: 2.1
Name: alphashapy
Version: 0.2.0
Summary: A Python package for constructing alpha shapes and alpha hulls for both positive and negative alphas.
Author: Itai Pelles
License: Apache-2.0
Project-URL: Homepage, https://github.com/itaipelles/alphashapy
Project-URL: Changelog, https://github.com/itaipelles/alphashapy/releases
Project-URL: Issues, https://github.com/itaipelles/alphashapy/issues
Project-URL: CI, https://github.com/itaipelles/alphashapy/actions
Classifier: License :: OSI Approved :: Apache Software License
Requires-Python: >=3.8
License-File: LICENSE
Requires-Dist: numpy
Requires-Dist: scipy
Requires-Dist: shapely
Provides-Extra: test
Requires-Dist: pytest ; extra == 'test'
